tests/__init__.py
tests/unit/__init__.py
tests/unit/abstract_test_case.py
ts_t1_validator/__init__.py
ts_t1_validator/utils.py
ts_t1_validator/__pycache__/__init__.cpython-39.pyc
ts_t1_validator/__pycache__/utils.cpython-39.pyc
ts_t1_validator/models/__init__.py
ts_t1_validator/models/__pycache__/__init__.cpython-39.pyc
ts_t1_validator/models/dto/__init__.py
ts_t1_validator/models/dto/campaign.py
ts_t1_validator/models/dto/strategy.py
ts_t1_validator/models/dto/targeting_location.py
ts_t1_validator/models/dto/__pycache__/__init__.cpython-39.pyc
ts_t1_validator/models/dto/__pycache__/campaign.cpython-39.pyc
ts_t1_validator/models/dto/__pycache__/strategy.cpython-39.pyc
ts_t1_validator/models/enums/__init__.py
ts_t1_validator/models/enums/abstract_enum.py
ts_t1_validator/models/enums/campaign_type.py
ts_t1_validator/models/enums/cap_type.py
ts_t1_validator/models/enums/dimension_action.py
ts_t1_validator/models/enums/dimension_code.py
ts_t1_validator/models/enums/frequency_interval.py
ts_t1_validator/models/enums/frequency_type.py
ts_t1_validator/models/enums/goal_type.py
ts_t1_validator/models/enums/impression_pacing_interval.py
ts_t1_validator/models/enums/impression_pacing_type.py
ts_t1_validator/models/enums/input_type.py
ts_t1_validator/models/enums/location_type.py
ts_t1_validator/models/enums/media_type.py
ts_t1_validator/models/enums/notification_type.py
ts_t1_validator/models/enums/pacing_interval.py
ts_t1_validator/models/enums/pacing_type.py
ts_t1_validator/models/enums/recurrence_type.py
ts_t1_validator/models/enums/strategy_type.py
ts_t1_validator/models/enums/switcher.py
ts_t1_validator/models/enums/targeting_included_type.py
ts_t1_validator/models/enums/targeting_type.py
ts_t1_validator/models/enums/validators.py
ts_t1_validator/models/enums/weekly_recurring_days.py
ts_t1_validator/models/enums/__pycache__/__init__.cpython-39.pyc
ts_t1_validator/models/enums/__pycache__/abstract_enum.cpython-39.pyc
ts_t1_validator-0.4.0.4.dist-info/LICENSE
ts_t1_validator-0.4.0.4.dist-info/METADATA
ts_t1_validator-0.4.0.4.dist-info/WHEEL
ts_t1_validator-0.4.0.4.dist-info/top_level.txt
ts_t1_validator-0.4.0.4.dist-info/RECORD
