Metadata-Version: 2.1
Name: ts-t1-validator
Version: 0.4.0.4
Summary: Validation logic for TerminalOne models used for api request models
Home-page: UNKNOWN
License: Apache License, Version 2.0
Platform: UNKNOWN
Requires-Python: >=3.6
License-File: LICENSE
Requires-Dist: python-dotenv
Requires-Dist: pytz
Requires-Dist: parameterized
Requires-Dist: faker
Requires-Dist: mock
Requires-Dist: requests
Requires-Dist: jsonschema
